<?xml version="1.0" encoding="utf-8" ?>
<content>
    <text><![CDATA[	
		<p><span class="popuptext">Herzog Carl II. (1804 in Braunschweig – 1873 in Genf), regierte von 1815 - 1830 in Braunschweig. Nach einem Aufstand der Braunschweiger Bevölkerung, dem auch das Schloss zum Opfer fiel, floh er und verbrachte den Rest seines Lebens in verschiedenen eurpäischen Ländern, bis er schließlich in Genf starb.</span></p> 
	]]></text>
	<img src="glossar/herzogcarlII.jpg" maxHeight="400" caption=" "/>
	  <text><![CDATA[	
		<p><span class="popuptext">„Metternich-Orden“ von Herzog Carl II. von Braunschweig und Lüneburg. Um 1825, Silber vergoldet, emailliert.</span></p> 
	]]></text>

</content>