<?xml version="1.0" encoding="utf-8" ?>
<content>
	<text><![CDATA[
		<p><span class="popuptext">Martin Luther (1483 in Eisleben - 1546 in Eisleben), Theologe, Reformator und Bibelübersetzer, zählt zu den einflussreichsten Persönlichkeiten des 16. Jahrhunderts, nördlich der Alpen „Reformationszeit“ genannt. Sein leidenschaftlicher Wunsch, die Kirche zu erneuern, entzündete sich am Ablasshandel, am materiellen Reichtum der Kirche und am Bau des prächtigen Petersdoms in Rom. Sein theologisches Interesse galt besonders der Frage nach Gottes Gerechtigkeit und der Rechtfertigung des Menschen vor Gott.</span></p>
	]]></text>
	<img src="glossar/martinluther.jpg" maxHeight="400" caption=" "/>
	<text><![CDATA[
		<p><span class="popuptext">Lukas Cranach d. Ä.: <i>Porträt des Martin Luther<i>, Rotbuchenholz, 1533, Braunschweig, Herzog Anton Ulrich-Museum.</span></p> 
	]]></text>
</content>